<?xml version="1.0" encoding="utf-8" ?><x:xmpmeta xmlns:x="adobe:ns:meta/" ><rdf:RDF xmlns:rdf="http://www.w3.org/1999/02/22-rdf-syntax-ns#" xmlns:xmp="http://ns.adobe.com/xap/1.0/" xmlns:xmpDM="http://ns.adobe.com/xmp/1.0/DynamicMedia/" xmlns:xmpG="http://ns.adobe.com/xap/1.0/g/" xmlns:tsc="http://www.techsmith.com/xmp/tsc/" xmlns:tscDM="http://www.techsmith.com/xmp/tscDM/" xmlns:tscHS="http://www.techsmith.com/xmp/tscHS/" xmlns:stDim="http://ns.adobe.com/xap/1.0/sType/Dimensions#" xmlns:stFnt="http://ns.adobe.com/xap/1.0/sType/Font#" xmlns:dc="http://purl.org/dc/elements/1.1/" ><rdf:Description tsc:version="2.0.0" dc:title="new-punctuation-video1-newest-fixed" dc:date="2017-12-19T14:51:56-6:00" dc:creator="" dc:Description="" dc:source="Camtasia Mac - 2.10.2" tscDM:iPodExplicit="false" tscDM:keywords="" tscDM:thumbnail="" tscDM:firstFrame="" ><xmpDM:duration xmpDM:scale="1/1000" xmpDM:value="566000" ></xmpDM:duration><xmpDM:videoFrameSize stDim:unit="pixel" stDim:w="1150" stDim:h="527" ></xmpDM:videoFrameSize><tsc:langName><rdf:Bag><rdf:li xml:lang="en">English</rdf:li><rdf:li xml:lang="en-US">English</rdf:li></rdf:Bag></tsc:langName><xmpDM:Tracks><rdf:Bag><rdf:li><rdf:Description xmpDM:trackType="Caption" xmpDM:frameRate="f1000" xmpDM:trackName="Captioning" stFnt:fontFamily="Arial" tscDM:fontSize="32" tscDM:bgOpacity="0.8" tscDM:position="overlay" tscDM:captionbarheight="46" ><xmpDM:markers><rdf:Seq><rdf:li><rdf:Description xmpDM:startTime="0" xmpDM:duration="566" tscDM:valign="bottom" tscDM:halign="center" ><xmpDM:name><rdf:Alt><rdf:li xml:lang="en">{\rtf1 }</rdf:li></rdf:Alt></xmpDM:name></rdf:Description></rdf:li><rdf:li><rdf:Description xmpDM:startTime="566" xmpDM:duration="2533" tscDM:valign="bottom" tscDM:halign="center" ><xmpDM:name><rdf:Alt><rdf:li xml:lang="en">{\rtf1 hi and welcome to the punctuation}</rdf:li></rdf:Alt></xmpDM:name></rdf:Description></rdf:li><rdf:li><rdf:Description xmpDM:startTime="3100" xmpDM:duration="1966" tscDM:valign="bottom" tscDM:halign="center" ><xmpDM:name><rdf:Alt><rdf:li xml:lang="en">{\rtf1 section of the course}</rdf:li></rdf:Alt></xmpDM:name></rdf:Description></rdf:li><rdf:li><rdf:Description xmpDM:startTime="5066" xmpDM:duration="4266" tscDM:valign="bottom" tscDM:halign="center" ><xmpDM:name><rdf:Alt><rdf:li xml:lang="en">{\rtf1 this is video 1 conjunctions and clauses}</rdf:li></rdf:Alt></xmpDM:name></rdf:Description></rdf:li><rdf:li><rdf:Description xmpDM:startTime="9333" xmpDM:duration="3333" tscDM:valign="bottom" tscDM:halign="center" ><xmpDM:name><rdf:Alt><rdf:li xml:lang="en">{\rtf1 just as a quick agenda item the first}</rdf:li></rdf:Alt></xmpDM:name></rdf:Description></rdf:li><rdf:li><rdf:Description xmpDM:startTime="12666" xmpDM:duration="1466" tscDM:valign="bottom" tscDM:halign="center" ><xmpDM:name><rdf:Alt><rdf:li xml:lang="en">{\rtf1 video with conjunctions and clauses}</rdf:li></rdf:Alt></xmpDM:name></rdf:Description></rdf:li><rdf:li><rdf:Description xmpDM:startTime="14133" xmpDM:duration="2966" tscDM:valign="bottom" tscDM:halign="center" ><xmpDM:name><rdf:Alt><rdf:li xml:lang="en">{\rtf1 video 2 is commas and then video 3 are}</rdf:li></rdf:Alt></xmpDM:name></rdf:Description></rdf:li><rdf:li><rdf:Description xmpDM:startTime="17100" xmpDM:duration="3166" tscDM:valign="bottom" tscDM:halign="center" ><xmpDM:name><rdf:Alt><rdf:li xml:lang="en">{\rtf1 other sort of less common punctuation}</rdf:li></rdf:Alt></xmpDM:name></rdf:Description></rdf:li><rdf:li><rdf:Description xmpDM:startTime="20266" xmpDM:duration="3466" tscDM:valign="bottom" tscDM:halign="center" ><xmpDM:name><rdf:Alt><rdf:li xml:lang="en">{\rtf1 types so today we&apos;ll look at}</rdf:li></rdf:Alt></xmpDM:name></rdf:Description></rdf:li><rdf:li><rdf:Description xmpDM:startTime="23733" xmpDM:duration="3766" tscDM:valign="bottom" tscDM:halign="center" ><xmpDM:name><rdf:Alt><rdf:li xml:lang="en">{\rtf1 conjunctions and cos clauses and just to}</rdf:li></rdf:Alt></xmpDM:name></rdf:Description></rdf:li><rdf:li><rdf:Description xmpDM:startTime="27500" xmpDM:duration="2200" tscDM:valign="bottom" tscDM:halign="center" ><xmpDM:name><rdf:Alt><rdf:li xml:lang="en">{\rtf1 lay down some foundational terminology}</rdf:li></rdf:Alt></xmpDM:name></rdf:Description></rdf:li><rdf:li><rdf:Description xmpDM:startTime="29700" xmpDM:duration="2466" tscDM:valign="bottom" tscDM:halign="center" ><xmpDM:name><rdf:Alt><rdf:li xml:lang="en">{\rtf1 clauses are something that must contain}</rdf:li></rdf:Alt></xmpDM:name></rdf:Description></rdf:li><rdf:li><rdf:Description xmpDM:startTime="32166" xmpDM:duration="2700" tscDM:valign="bottom" tscDM:halign="center" ><xmpDM:name><rdf:Alt><rdf:li xml:lang="en">{\rtf1 a subject and a predicate and so in the}</rdf:li></rdf:Alt></xmpDM:name></rdf:Description></rdf:li><rdf:li><rdf:Description xmpDM:startTime="34866" xmpDM:duration="1433" tscDM:valign="bottom" tscDM:halign="center" ><xmpDM:name><rdf:Alt><rdf:li xml:lang="en">{\rtf1 grammar videos in the grammar section}</rdf:li></rdf:Alt></xmpDM:name></rdf:Description></rdf:li><rdf:li><rdf:Description xmpDM:startTime="36300" xmpDM:duration="3466" tscDM:valign="bottom" tscDM:halign="center" ><xmpDM:name><rdf:Alt><rdf:li xml:lang="en">{\rtf1 last week we talked about subjects and}</rdf:li></rdf:Alt></xmpDM:name></rdf:Description></rdf:li><rdf:li><rdf:Description xmpDM:startTime="39766" xmpDM:duration="2800" tscDM:valign="bottom" tscDM:halign="center" ><xmpDM:name><rdf:Alt><rdf:li xml:lang="en">{\rtf1 predicates but just as a as a refresher}</rdf:li></rdf:Alt></xmpDM:name></rdf:Description></rdf:li><rdf:li><rdf:Description xmpDM:startTime="42566" xmpDM:duration="2033" tscDM:valign="bottom" tscDM:halign="center" ><xmpDM:name><rdf:Alt><rdf:li xml:lang="en">{\rtf1 subjects or nouns or something nouns}</rdf:li></rdf:Alt></xmpDM:name></rdf:Description></rdf:li><rdf:li><rdf:Description xmpDM:startTime="44600" xmpDM:duration="2833" tscDM:valign="bottom" tscDM:halign="center" ><xmpDM:name><rdf:Alt><rdf:li xml:lang="en">{\rtf1 like and a predicate is something about}</rdf:li></rdf:Alt></xmpDM:name></rdf:Description></rdf:li><rdf:li><rdf:Description xmpDM:startTime="47433" xmpDM:duration="2933" tscDM:valign="bottom" tscDM:halign="center" ><xmpDM:name><rdf:Alt><rdf:li xml:lang="en">{\rtf1 the subject and must have a verb so just}</rdf:li></rdf:Alt></xmpDM:name></rdf:Description></rdf:li><rdf:li><rdf:Description xmpDM:startTime="50366" xmpDM:duration="2100" tscDM:valign="bottom" tscDM:halign="center" ><xmpDM:name><rdf:Alt><rdf:li xml:lang="en">{\rtf1 to refresh our memory that&apos;s what we say}</rdf:li></rdf:Alt></xmpDM:name></rdf:Description></rdf:li><rdf:li><rdf:Description xmpDM:startTime="52466" xmpDM:duration="2333" tscDM:valign="bottom" tscDM:halign="center" ><xmpDM:name><rdf:Alt><rdf:li xml:lang="en">{\rtf1 clause we&apos;re saying it&apos;s something that}</rdf:li></rdf:Alt></xmpDM:name></rdf:Description></rdf:li><rdf:li><rdf:Description xmpDM:startTime="54800" xmpDM:duration="2500" tscDM:valign="bottom" tscDM:halign="center" ><xmpDM:name><rdf:Alt><rdf:li xml:lang="en">{\rtf1 has a subject and a predicate and really}</rdf:li></rdf:Alt></xmpDM:name></rdf:Description></rdf:li><rdf:li><rdf:Description xmpDM:startTime="57300" xmpDM:duration="1666" tscDM:valign="bottom" tscDM:halign="center" ><xmpDM:name><rdf:Alt><rdf:li xml:lang="en">{\rtf1 there&apos;s two types of clauses here}</rdf:li></rdf:Alt></xmpDM:name></rdf:Description></rdf:li><rdf:li><rdf:Description xmpDM:startTime="58966" xmpDM:duration="2533" tscDM:valign="bottom" tscDM:halign="center" ><xmpDM:name><rdf:Alt><rdf:li xml:lang="en">{\rtf1 there&apos;s the independent clause these are}</rdf:li></rdf:Alt></xmpDM:name></rdf:Description></rdf:li><rdf:li><rdf:Description xmpDM:startTime="61500" xmpDM:duration="1700" tscDM:valign="bottom" tscDM:halign="center" ><xmpDM:name><rdf:Alt><rdf:li xml:lang="en">{\rtf1 clauses that can stand alone as a}</rdf:li></rdf:Alt></xmpDM:name></rdf:Description></rdf:li><rdf:li><rdf:Description xmpDM:startTime="63200" xmpDM:duration="3033" tscDM:valign="bottom" tscDM:halign="center" ><xmpDM:name><rdf:Alt><rdf:li xml:lang="en">{\rtf1 sentence so the examples a student slept}</rdf:li></rdf:Alt></xmpDM:name></rdf:Description></rdf:li><rdf:li><rdf:Description xmpDM:startTime="66233" xmpDM:duration="2133" tscDM:valign="bottom" tscDM:halign="center" ><xmpDM:name><rdf:Alt><rdf:li xml:lang="en">{\rtf1 in class that can expand it alone as a}</rdf:li></rdf:Alt></xmpDM:name></rdf:Description></rdf:li><rdf:li><rdf:Description xmpDM:startTime="68366" xmpDM:duration="1666" tscDM:valign="bottom" tscDM:halign="center" ><xmpDM:name><rdf:Alt><rdf:li xml:lang="en">{\rtf1 sentence it&apos;s going to subject the}</rdf:li></rdf:Alt></xmpDM:name></rdf:Description></rdf:li><rdf:li><rdf:Description xmpDM:startTime="70033" xmpDM:duration="2866" tscDM:valign="bottom" tscDM:halign="center" ><xmpDM:name><rdf:Alt><rdf:li xml:lang="en">{\rtf1 student and it&apos;s got a predicate slept}</rdf:li></rdf:Alt></xmpDM:name></rdf:Description></rdf:li><rdf:li><rdf:Description xmpDM:startTime="72900" xmpDM:duration="2966" tscDM:valign="bottom" tscDM:halign="center" ><xmpDM:name><rdf:Alt><rdf:li xml:lang="en">{\rtf1 in class and put together it&apos;s a}</rdf:li></rdf:Alt></xmpDM:name></rdf:Description></rdf:li><rdf:li><rdf:Description xmpDM:startTime="75866" xmpDM:duration="3633" tscDM:valign="bottom" tscDM:halign="center" ><xmpDM:name><rdf:Alt><rdf:li xml:lang="en">{\rtf1 grammatical sentence on the other hand}</rdf:li></rdf:Alt></xmpDM:name></rdf:Description></rdf:li><rdf:li><rdf:Description xmpDM:startTime="79500" xmpDM:duration="2400" tscDM:valign="bottom" tscDM:halign="center" ><xmpDM:name><rdf:Alt><rdf:li xml:lang="en">{\rtf1 we&apos;ve got also dependent clauses also}</rdf:li></rdf:Alt></xmpDM:name></rdf:Description></rdf:li><rdf:li><rdf:Description xmpDM:startTime="81900" xmpDM:duration="3166" tscDM:valign="bottom" tscDM:halign="center" ><xmpDM:name><rdf:Alt><rdf:li xml:lang="en">{\rtf1 known as subordinate clauses these are}</rdf:li></rdf:Alt></xmpDM:name></rdf:Description></rdf:li><rdf:li><rdf:Description xmpDM:startTime="85066" xmpDM:duration="1866" tscDM:valign="bottom" tscDM:halign="center" ><xmpDM:name><rdf:Alt><rdf:li xml:lang="en">{\rtf1 clauses that can&apos;t stand alone as a}</rdf:li></rdf:Alt></xmpDM:name></rdf:Description></rdf:li><rdf:li><rdf:Description xmpDM:startTime="86933" xmpDM:duration="2333" tscDM:valign="bottom" tscDM:halign="center" ><xmpDM:name><rdf:Alt><rdf:li xml:lang="en">{\rtf1 sentence they need some additional}</rdf:li></rdf:Alt></xmpDM:name></rdf:Description></rdf:li><rdf:li><rdf:Description xmpDM:startTime="89266" xmpDM:duration="3500" tscDM:valign="bottom" tscDM:halign="center" ><xmpDM:name><rdf:Alt><rdf:li xml:lang="en">{\rtf1 content some additional information for}</rdf:li></rdf:Alt></xmpDM:name></rdf:Description></rdf:li><rdf:li><rdf:Description xmpDM:startTime="92766" xmpDM:duration="1433" tscDM:valign="bottom" tscDM:halign="center" ><xmpDM:name><rdf:Alt><rdf:li xml:lang="en">{\rtf1 it to stand alone grammatically as a}</rdf:li></rdf:Alt></xmpDM:name></rdf:Description></rdf:li><rdf:li><rdf:Description xmpDM:startTime="94200" xmpDM:duration="2900" tscDM:valign="bottom" tscDM:halign="center" ><xmpDM:name><rdf:Alt><rdf:li xml:lang="en">{\rtf1 sentence so an example of this is while}</rdf:li></rdf:Alt></xmpDM:name></rdf:Description></rdf:li><rdf:li><rdf:Description xmpDM:startTime="97100" xmpDM:duration="2400" tscDM:valign="bottom" tscDM:halign="center" ><xmpDM:name><rdf:Alt><rdf:li xml:lang="en">{\rtf1 the student slept in class right we}</rdf:li></rdf:Alt></xmpDM:name></rdf:Description></rdf:li><rdf:li><rdf:Description xmpDM:startTime="99500" xmpDM:duration="1633" tscDM:valign="bottom" tscDM:halign="center" ><xmpDM:name><rdf:Alt><rdf:li xml:lang="en">{\rtf1 couldn&apos;t just punctuate that and call it}</rdf:li></rdf:Alt></xmpDM:name></rdf:Description></rdf:li><rdf:li><rdf:Description xmpDM:startTime="101133" xmpDM:duration="3600" tscDM:valign="bottom" tscDM:halign="center" ><xmpDM:name><rdf:Alt><rdf:li xml:lang="en">{\rtf1 a sentence but it does actually have a}</rdf:li></rdf:Alt></xmpDM:name></rdf:Description></rdf:li><rdf:li><rdf:Description xmpDM:startTime="104733" xmpDM:duration="2400" tscDM:valign="bottom" tscDM:halign="center" ><xmpDM:name><rdf:Alt><rdf:li xml:lang="en">{\rtf1 subject the student and it has a}</rdf:li></rdf:Alt></xmpDM:name></rdf:Description></rdf:li><rdf:li><rdf:Description xmpDM:startTime="107133" xmpDM:duration="4066" tscDM:valign="bottom" tscDM:halign="center" ><xmpDM:name><rdf:Alt><rdf:li xml:lang="en">{\rtf1 predicate it&apos;s got a predicate with a}</rdf:li></rdf:Alt></xmpDM:name></rdf:Description></rdf:li><rdf:li><rdf:Description xmpDM:startTime="111200" xmpDM:duration="4000" tscDM:valign="bottom" tscDM:halign="center" ><xmpDM:name><rdf:Alt><rdf:li xml:lang="en">{\rtf1 verb phrase slept in class and so we&apos;ve}</rdf:li></rdf:Alt></xmpDM:name></rdf:Description></rdf:li><rdf:li><rdf:Description xmpDM:startTime="115200" xmpDM:duration="1833" tscDM:valign="bottom" tscDM:halign="center" ><xmpDM:name><rdf:Alt><rdf:li xml:lang="en">{\rtf1 got these two different clauses}</rdf:li></rdf:Alt></xmpDM:name></rdf:Description></rdf:li><rdf:li><rdf:Description xmpDM:startTime="117033" xmpDM:duration="2033" tscDM:valign="bottom" tscDM:halign="center" ><xmpDM:name><rdf:Alt><rdf:li xml:lang="en">{\rtf1 independent clauses and dependent}</rdf:li></rdf:Alt></xmpDM:name></rdf:Description></rdf:li><rdf:li><rdf:Description xmpDM:startTime="119066" xmpDM:duration="3300" tscDM:valign="bottom" tscDM:halign="center" ><xmpDM:name><rdf:Alt><rdf:li xml:lang="en">{\rtf1 clauses easy way that I remember this}</rdf:li></rdf:Alt></xmpDM:name></rdf:Description></rdf:li><rdf:li><rdf:Description xmpDM:startTime="122366" xmpDM:duration="3633" tscDM:valign="bottom" tscDM:halign="center" ><xmpDM:name><rdf:Alt><rdf:li xml:lang="en">{\rtf1 and it may be obvious but dependent}</rdf:li></rdf:Alt></xmpDM:name></rdf:Description></rdf:li><rdf:li><rdf:Description xmpDM:startTime="126000" xmpDM:duration="2333" tscDM:valign="bottom" tscDM:halign="center" ><xmpDM:name><rdf:Alt><rdf:li xml:lang="en">{\rtf1 clauses depend on something else for}</rdf:li></rdf:Alt></xmpDM:name></rdf:Description></rdf:li><rdf:li><rdf:Description xmpDM:startTime="128333" xmpDM:duration="1833" tscDM:valign="bottom" tscDM:halign="center" ><xmpDM:name><rdf:Alt><rdf:li xml:lang="en">{\rtf1 them to become a full sentence so just}</rdf:li></rdf:Alt></xmpDM:name></rdf:Description></rdf:li><rdf:li><rdf:Description xmpDM:startTime="130166" xmpDM:duration="2133" tscDM:valign="bottom" tscDM:halign="center" ><xmpDM:name><rdf:Alt><rdf:li xml:lang="en">{\rtf1 as a quick way of remember memorizing or}</rdf:li></rdf:Alt></xmpDM:name></rdf:Description></rdf:li><rdf:li><rdf:Description xmpDM:startTime="132300" xmpDM:duration="800" tscDM:valign="bottom" tscDM:halign="center" ><xmpDM:name><rdf:Alt><rdf:li xml:lang="en">{\rtf1 remembering the}</rdf:li></rdf:Alt></xmpDM:name></rdf:Description></rdf:li><rdf:li><rdf:Description xmpDM:startTime="133100" xmpDM:duration="1033" tscDM:valign="bottom" tscDM:halign="center" ><xmpDM:name><rdf:Alt><rdf:li xml:lang="en">{\rtf1 it&apos;s between the two that&apos;s how I}</rdf:li></rdf:Alt></xmpDM:name></rdf:Description></rdf:li><rdf:li><rdf:Description xmpDM:startTime="134133" xmpDM:duration="3966" tscDM:valign="bottom" tscDM:halign="center" ><xmpDM:name><rdf:Alt><rdf:li xml:lang="en">{\rtf1 remember okay let&apos;s take a second here}</rdf:li></rdf:Alt></xmpDM:name></rdf:Description></rdf:li><rdf:li><rdf:Description xmpDM:startTime="138100" xmpDM:duration="2466" tscDM:valign="bottom" tscDM:halign="center" ><xmpDM:name><rdf:Alt><rdf:li xml:lang="en">{\rtf1 and do a quick practice exercise go}</rdf:li></rdf:Alt></xmpDM:name></rdf:Description></rdf:li><rdf:li><rdf:Description xmpDM:startTime="140566" xmpDM:duration="2100" tscDM:valign="bottom" tscDM:halign="center" ><xmpDM:name><rdf:Alt><rdf:li xml:lang="en">{\rtf1 ahead and click anywhere on the video}</rdf:li></rdf:Alt></xmpDM:name></rdf:Description></rdf:li><rdf:li><rdf:Description xmpDM:startTime="142666" xmpDM:duration="3333" tscDM:valign="bottom" tscDM:halign="center" ><xmpDM:name><rdf:Alt><rdf:li xml:lang="en">{\rtf1 screen to launch the practice exercise}</rdf:li></rdf:Alt></xmpDM:name></rdf:Description></rdf:li><rdf:li><rdf:Description xmpDM:startTime="146000" xmpDM:duration="2100" tscDM:valign="bottom" tscDM:halign="center" ><xmpDM:name><rdf:Alt><rdf:li xml:lang="en">{\rtf1 okay so now that we have foundational}</rdf:li></rdf:Alt></xmpDM:name></rdf:Description></rdf:li><rdf:li><rdf:Description xmpDM:startTime="148100" xmpDM:duration="1466" tscDM:valign="bottom" tscDM:halign="center" ><xmpDM:name><rdf:Alt><rdf:li xml:lang="en">{\rtf1 terminology what we&apos;ll do is we&apos;ll look}</rdf:li></rdf:Alt></xmpDM:name></rdf:Description></rdf:li><rdf:li><rdf:Description xmpDM:startTime="149566" xmpDM:duration="2966" tscDM:valign="bottom" tscDM:halign="center" ><xmpDM:name><rdf:Alt><rdf:li xml:lang="en">{\rtf1 at three types of conjunctions so a}</rdf:li></rdf:Alt></xmpDM:name></rdf:Description></rdf:li><rdf:li><rdf:Description xmpDM:startTime="152533" xmpDM:duration="2633" tscDM:valign="bottom" tscDM:halign="center" ><xmpDM:name><rdf:Alt><rdf:li xml:lang="en">{\rtf1 conjunction is a word that joins two or}</rdf:li></rdf:Alt></xmpDM:name></rdf:Description></rdf:li><rdf:li><rdf:Description xmpDM:startTime="155166" xmpDM:duration="2233" tscDM:valign="bottom" tscDM:halign="center" ><xmpDM:name><rdf:Alt><rdf:li xml:lang="en">{\rtf1 more clauses together we&apos;re and we&apos;ll}</rdf:li></rdf:Alt></xmpDM:name></rdf:Description></rdf:li><rdf:li><rdf:Description xmpDM:startTime="157400" xmpDM:duration="1800" tscDM:valign="bottom" tscDM:halign="center" ><xmpDM:name><rdf:Alt><rdf:li xml:lang="en">{\rtf1 typically just look at two clauses in}</rdf:li></rdf:Alt></xmpDM:name></rdf:Description></rdf:li><rdf:li><rdf:Description xmpDM:startTime="159200" xmpDM:duration="1966" tscDM:valign="bottom" tscDM:halign="center" ><xmpDM:name><rdf:Alt><rdf:li xml:lang="en">{\rtf1 this class because that&apos;s usually how}</rdf:li></rdf:Alt></xmpDM:name></rdf:Description></rdf:li><rdf:li><rdf:Description xmpDM:startTime="161166" xmpDM:duration="2800" tscDM:valign="bottom" tscDM:halign="center" ><xmpDM:name><rdf:Alt><rdf:li xml:lang="en">{\rtf1 sentences are constructed is with two}</rdf:li></rdf:Alt></xmpDM:name></rdf:Description></rdf:li><rdf:li><rdf:Description xmpDM:startTime="163966" xmpDM:duration="2500" tscDM:valign="bottom" tscDM:halign="center" ><xmpDM:name><rdf:Alt><rdf:li xml:lang="en">{\rtf1 clauses but sometimes there&apos;s more and}</rdf:li></rdf:Alt></xmpDM:name></rdf:Description></rdf:li><rdf:li><rdf:Description xmpDM:startTime="166466" xmpDM:duration="1666" tscDM:valign="bottom" tscDM:halign="center" ><xmpDM:name><rdf:Alt><rdf:li xml:lang="en">{\rtf1 so we&apos;re looking at three types of}</rdf:li></rdf:Alt></xmpDM:name></rdf:Description></rdf:li><rdf:li><rdf:Description xmpDM:startTime="168133" xmpDM:duration="1866" tscDM:valign="bottom" tscDM:halign="center" ><xmpDM:name><rdf:Alt><rdf:li xml:lang="en">{\rtf1 conjunctions or three types of words}</rdf:li></rdf:Alt></xmpDM:name></rdf:Description></rdf:li><rdf:li><rdf:Description xmpDM:startTime="170000" xmpDM:duration="3300" tscDM:valign="bottom" tscDM:halign="center" ><xmpDM:name><rdf:Alt><rdf:li xml:lang="en">{\rtf1 that join clauses together the first is}</rdf:li></rdf:Alt></xmpDM:name></rdf:Description></rdf:li><rdf:li><rdf:Description xmpDM:startTime="173300" xmpDM:duration="1266" tscDM:valign="bottom" tscDM:halign="center" ><xmpDM:name><rdf:Alt><rdf:li xml:lang="en">{\rtf1 coordinating conjunctions}</rdf:li></rdf:Alt></xmpDM:name></rdf:Description></rdf:li><rdf:li><rdf:Description xmpDM:startTime="174566" xmpDM:duration="1800" tscDM:valign="bottom" tscDM:halign="center" ><xmpDM:name><rdf:Alt><rdf:li xml:lang="en">{\rtf1 the second are sub ordinate in}</rdf:li></rdf:Alt></xmpDM:name></rdf:Description></rdf:li><rdf:li><rdf:Description xmpDM:startTime="176366" xmpDM:duration="1933" tscDM:valign="bottom" tscDM:halign="center" ><xmpDM:name><rdf:Alt><rdf:li xml:lang="en">{\rtf1 conjunction and the third are}</rdf:li></rdf:Alt></xmpDM:name></rdf:Description></rdf:li><rdf:li><rdf:Description xmpDM:startTime="178300" xmpDM:duration="2033" tscDM:valign="bottom" tscDM:halign="center" ><xmpDM:name><rdf:Alt><rdf:li xml:lang="en">{\rtf1 conjunctive adverbs}</rdf:li></rdf:Alt></xmpDM:name></rdf:Description></rdf:li><rdf:li><rdf:Description xmpDM:startTime="180333" xmpDM:duration="4000" tscDM:valign="bottom" tscDM:halign="center" ><xmpDM:name><rdf:Alt><rdf:li xml:lang="en">{\rtf1 so coordinating conjunctions they join}</rdf:li></rdf:Alt></xmpDM:name></rdf:Description></rdf:li><rdf:li><rdf:Description xmpDM:startTime="184333" xmpDM:duration="2300" tscDM:valign="bottom" tscDM:halign="center" ><xmpDM:name><rdf:Alt><rdf:li xml:lang="en">{\rtf1 two independent clauses or sentences}</rdf:li></rdf:Alt></xmpDM:name></rdf:Description></rdf:li><rdf:li><rdf:Description xmpDM:startTime="186633" xmpDM:duration="2800" tscDM:valign="bottom" tscDM:halign="center" ><xmpDM:name><rdf:Alt><rdf:li xml:lang="en">{\rtf1 sentence elements okay so if you&apos;ve got}</rdf:li></rdf:Alt></xmpDM:name></rdf:Description></rdf:li><rdf:li><rdf:Description xmpDM:startTime="189433" xmpDM:duration="3166" tscDM:valign="bottom" tscDM:halign="center" ><xmpDM:name><rdf:Alt><rdf:li xml:lang="en">{\rtf1 two independent clauses two clauses that}</rdf:li></rdf:Alt></xmpDM:name></rdf:Description></rdf:li><rdf:li><rdf:Description xmpDM:startTime="192600" xmpDM:duration="2466" tscDM:valign="bottom" tscDM:halign="center" ><xmpDM:name><rdf:Alt><rdf:li xml:lang="en">{\rtf1 can stand alone as sentences you can}</rdf:li></rdf:Alt></xmpDM:name></rdf:Description></rdf:li><rdf:li><rdf:Description xmpDM:startTime="195066" xmpDM:duration="2333" tscDM:valign="bottom" tscDM:halign="center" ><xmpDM:name><rdf:Alt><rdf:li xml:lang="en">{\rtf1 connect them with coordinating}</rdf:li></rdf:Alt></xmpDM:name></rdf:Description></rdf:li><rdf:li><rdf:Description xmpDM:startTime="197400" xmpDM:duration="4200" tscDM:valign="bottom" tscDM:halign="center" ><xmpDM:name><rdf:Alt><rdf:li xml:lang="en">{\rtf1 conjunctions an easy way to remember the}</rdf:li></rdf:Alt></xmpDM:name></rdf:Description></rdf:li><rdf:li><rdf:Description xmpDM:startTime="201600" xmpDM:duration="1433" tscDM:valign="bottom" tscDM:halign="center" ><xmpDM:name><rdf:Alt><rdf:li xml:lang="en">{\rtf1 so coordinating conjunctions are a}</rdf:li></rdf:Alt></xmpDM:name></rdf:Description></rdf:li><rdf:li><rdf:Description xmpDM:startTime="203033" xmpDM:duration="3400" tscDM:valign="bottom" tscDM:halign="center" ><xmpDM:name><rdf:Alt><rdf:li xml:lang="en">{\rtf1 finite list of of words and an easy}</rdf:li></rdf:Alt></xmpDM:name></rdf:Description></rdf:li><rdf:li><rdf:Description xmpDM:startTime="206433" xmpDM:duration="3233" tscDM:valign="bottom" tscDM:halign="center" ><xmpDM:name><rdf:Alt><rdf:li xml:lang="en">{\rtf1 acronym to remember is fanboys and so}</rdf:li></rdf:Alt></xmpDM:name></rdf:Description></rdf:li><rdf:li><rdf:Description xmpDM:startTime="209666" xmpDM:duration="1933" tscDM:valign="bottom" tscDM:halign="center" ><xmpDM:name><rdf:Alt><rdf:li xml:lang="en">{\rtf1 here&apos;s a picture of Apple fanboys to}</rdf:li></rdf:Alt></xmpDM:name></rdf:Description></rdf:li><rdf:li><rdf:Description xmpDM:startTime="211600" xmpDM:duration="2966" tscDM:valign="bottom" tscDM:halign="center" ><xmpDM:name><rdf:Alt><rdf:li xml:lang="en">{\rtf1 help you remember this but fanboys}</rdf:li></rdf:Alt></xmpDM:name></rdf:Description></rdf:li><rdf:li><rdf:Description xmpDM:startTime="214566" xmpDM:duration="4333" tscDM:valign="bottom" tscDM:halign="center" ><xmpDM:name><rdf:Alt><rdf:li xml:lang="en">{\rtf1 stands for for and nor but or yet and so}</rdf:li></rdf:Alt></xmpDM:name></rdf:Description></rdf:li><rdf:li><rdf:Description xmpDM:startTime="218900" xmpDM:duration="1733" tscDM:valign="bottom" tscDM:halign="center" ><xmpDM:name><rdf:Alt><rdf:li xml:lang="en">{\rtf1 so we&apos;ve got a finite number of}</rdf:li></rdf:Alt></xmpDM:name></rdf:Description></rdf:li><rdf:li><rdf:Description xmpDM:startTime="220633" xmpDM:duration="3366" tscDM:valign="bottom" tscDM:halign="center" ><xmpDM:name><rdf:Alt><rdf:li xml:lang="en">{\rtf1 coordinating conjunctions easy to}</rdf:li></rdf:Alt></xmpDM:name></rdf:Description></rdf:li><rdf:li><rdf:Description xmpDM:startTime="224000" xmpDM:duration="2966" tscDM:valign="bottom" tscDM:halign="center" ><xmpDM:name><rdf:Alt><rdf:li xml:lang="en">{\rtf1 remember if you can remember fanboys}</rdf:li></rdf:Alt></xmpDM:name></rdf:Description></rdf:li><rdf:li><rdf:Description xmpDM:startTime="226966" xmpDM:duration="3033" tscDM:valign="bottom" tscDM:halign="center" ><xmpDM:name><rdf:Alt><rdf:li xml:lang="en">{\rtf1 okay so some punctuation considerations}</rdf:li></rdf:Alt></xmpDM:name></rdf:Description></rdf:li><rdf:li><rdf:Description xmpDM:startTime="230000" xmpDM:duration="2200" tscDM:valign="bottom" tscDM:halign="center" ><xmpDM:name><rdf:Alt><rdf:li xml:lang="en">{\rtf1 really there&apos;s two really there&apos;s two}</rdf:li></rdf:Alt></xmpDM:name></rdf:Description></rdf:li><rdf:li><rdf:Description xmpDM:startTime="232200" xmpDM:duration="2033" tscDM:valign="bottom" tscDM:halign="center" ><xmpDM:name><rdf:Alt><rdf:li xml:lang="en">{\rtf1 things to think about whether or not we}</rdf:li></rdf:Alt></xmpDM:name></rdf:Description></rdf:li><rdf:li><rdf:Description xmpDM:startTime="234233" xmpDM:duration="2600" tscDM:valign="bottom" tscDM:halign="center" ><xmpDM:name><rdf:Alt><rdf:li xml:lang="en">{\rtf1 should use a comma or whether or not we}</rdf:li></rdf:Alt></xmpDM:name></rdf:Description></rdf:li><rdf:li><rdf:Description xmpDM:startTime="236833" xmpDM:duration="2233" tscDM:valign="bottom" tscDM:halign="center" ><xmpDM:name><rdf:Alt><rdf:li xml:lang="en">{\rtf1 should leave the comma out so we leave}</rdf:li></rdf:Alt></xmpDM:name></rdf:Description></rdf:li><rdf:li><rdf:Description xmpDM:startTime="239066" xmpDM:duration="1800" tscDM:valign="bottom" tscDM:halign="center" ><xmpDM:name><rdf:Alt><rdf:li xml:lang="en">{\rtf1 the comma out if it&apos;s a compound}</rdf:li></rdf:Alt></xmpDM:name></rdf:Description></rdf:li><rdf:li><rdf:Description xmpDM:startTime="240866" xmpDM:duration="2266" tscDM:valign="bottom" tscDM:halign="center" ><xmpDM:name><rdf:Alt><rdf:li xml:lang="en">{\rtf1 predicate so if you&apos;ve got a sentence}</rdf:li></rdf:Alt></xmpDM:name></rdf:Description></rdf:li><rdf:li><rdf:Description xmpDM:startTime="243133" xmpDM:duration="2333" tscDM:valign="bottom" tscDM:halign="center" ><xmpDM:name><rdf:Alt><rdf:li xml:lang="en">{\rtf1 where you&apos;ve got one subject that&apos;s}</rdf:li></rdf:Alt></xmpDM:name></rdf:Description></rdf:li><rdf:li><rdf:Description xmpDM:startTime="245466" xmpDM:duration="2700" tscDM:valign="bottom" tscDM:halign="center" ><xmpDM:name><rdf:Alt><rdf:li xml:lang="en">{\rtf1 doing two different verb phrases so}</rdf:li></rdf:Alt></xmpDM:name></rdf:Description></rdf:li><rdf:li><rdf:Description xmpDM:startTime="248166" xmpDM:duration="2400" tscDM:valign="bottom" tscDM:halign="center" ><xmpDM:name><rdf:Alt><rdf:li xml:lang="en">{\rtf1 here&apos;s an example I went to the park and}</rdf:li></rdf:Alt></xmpDM:name></rdf:Description></rdf:li><rdf:li><rdf:Description xmpDM:startTime="250566" xmpDM:duration="2866" tscDM:valign="bottom" tscDM:halign="center" ><xmpDM:name><rdf:Alt><rdf:li xml:lang="en">{\rtf1 ate ice cream right so went to the park}</rdf:li></rdf:Alt></xmpDM:name></rdf:Description></rdf:li><rdf:li><rdf:Description xmpDM:startTime="253433" xmpDM:duration="2000" tscDM:valign="bottom" tscDM:halign="center" ><xmpDM:name><rdf:Alt><rdf:li xml:lang="en">{\rtf1 is one verb phrase ate ice cream is our}</rdf:li></rdf:Alt></xmpDM:name></rdf:Description></rdf:li><rdf:li><rdf:Description xmpDM:startTime="255433" xmpDM:duration="1800" tscDM:valign="bottom" tscDM:halign="center" ><xmpDM:name><rdf:Alt><rdf:li xml:lang="en">{\rtf1 second verb phrase that&apos;s connected by}</rdf:li></rdf:Alt></xmpDM:name></rdf:Description></rdf:li><rdf:li><rdf:Description xmpDM:startTime="257233" xmpDM:duration="2633" tscDM:valign="bottom" tscDM:halign="center" ><xmpDM:name><rdf:Alt><rdf:li xml:lang="en">{\rtf1 this coordinating conjunction and don&apos;t}</rdf:li></rdf:Alt></xmpDM:name></rdf:Description></rdf:li><rdf:li><rdf:Description xmpDM:startTime="259866" xmpDM:duration="4233" tscDM:valign="bottom" tscDM:halign="center" ><xmpDM:name><rdf:Alt><rdf:li xml:lang="en">{\rtf1 it does not need a comma however if we}</rdf:li></rdf:Alt></xmpDM:name></rdf:Description></rdf:li><rdf:li><rdf:Description xmpDM:startTime="264100" xmpDM:duration="2566" tscDM:valign="bottom" tscDM:halign="center" ><xmpDM:name><rdf:Alt><rdf:li xml:lang="en">{\rtf1 reintroduced the subject or we}</rdf:li></rdf:Alt></xmpDM:name></rdf:Description></rdf:li><rdf:li><rdf:Description xmpDM:startTime="266666" xmpDM:duration="3000" tscDM:valign="bottom" tscDM:halign="center" ><xmpDM:name><rdf:Alt><rdf:li xml:lang="en">{\rtf1 we introduced a new subject we must}</rdf:li></rdf:Alt></xmpDM:name></rdf:Description></rdf:li><rdf:li><rdf:Description xmpDM:startTime="269666" xmpDM:duration="1700" tscDM:valign="bottom" tscDM:halign="center" ><xmpDM:name><rdf:Alt><rdf:li xml:lang="en">{\rtf1 include a comma before the coordinating}</rdf:li></rdf:Alt></xmpDM:name></rdf:Description></rdf:li><rdf:li><rdf:Description xmpDM:startTime="271366" xmpDM:duration="3166" tscDM:valign="bottom" tscDM:halign="center" ><xmpDM:name><rdf:Alt><rdf:li xml:lang="en">{\rtf1 conjunction so our example I went to the}</rdf:li></rdf:Alt></xmpDM:name></rdf:Description></rdf:li><rdf:li><rdf:Description xmpDM:startTime="274533" xmpDM:duration="3166" tscDM:valign="bottom" tscDM:halign="center" ><xmpDM:name><rdf:Alt><rdf:li xml:lang="en">{\rtf1 park comma and I ate ice cream because}</rdf:li></rdf:Alt></xmpDM:name></rdf:Description></rdf:li><rdf:li><rdf:Description xmpDM:startTime="277700" xmpDM:duration="2366" tscDM:valign="bottom" tscDM:halign="center" ><xmpDM:name><rdf:Alt><rdf:li xml:lang="en">{\rtf1 we have that word I in there we&apos;re}</rdf:li></rdf:Alt></xmpDM:name></rdf:Description></rdf:li><rdf:li><rdf:Description xmpDM:startTime="280066" xmpDM:duration="4200" tscDM:valign="bottom" tscDM:halign="center" ><xmpDM:name><rdf:Alt><rdf:li xml:lang="en">{\rtf1 reintroducing the subject I it must take}</rdf:li></rdf:Alt></xmpDM:name></rdf:Description></rdf:li><rdf:li><rdf:Description xmpDM:startTime="284266" xmpDM:duration="4700" tscDM:valign="bottom" tscDM:halign="center" ><xmpDM:name><rdf:Alt><rdf:li xml:lang="en">{\rtf1 a comma and so if you just removed the}</rdf:li></rdf:Alt></xmpDM:name></rdf:Description></rdf:li><rdf:li><rdf:Description xmpDM:startTime="288966" xmpDM:duration="1600" tscDM:valign="bottom" tscDM:halign="center" ><xmpDM:name><rdf:Alt><rdf:li xml:lang="en">{\rtf1 coordinating conjunction you have two}</rdf:li></rdf:Alt></xmpDM:name></rdf:Description></rdf:li><rdf:li><rdf:Description xmpDM:startTime="290566" xmpDM:duration="2633" tscDM:valign="bottom" tscDM:halign="center" ><xmpDM:name><rdf:Alt><rdf:li xml:lang="en">{\rtf1 completely independent clauses I went to}</rdf:li></rdf:Alt></xmpDM:name></rdf:Description></rdf:li><rdf:li><rdf:Description xmpDM:startTime="293200" xmpDM:duration="500" tscDM:valign="bottom" tscDM:halign="center" ><xmpDM:name><rdf:Alt><rdf:li xml:lang="en">{\rtf1 the park}</rdf:li></rdf:Alt></xmpDM:name></rdf:Description></rdf:li><rdf:li><rdf:Description xmpDM:startTime="293700" xmpDM:duration="2233" tscDM:valign="bottom" tscDM:halign="center" ><xmpDM:name><rdf:Alt><rdf:li xml:lang="en">{\rtf1 I ate ice cream right so those are two}</rdf:li></rdf:Alt></xmpDM:name></rdf:Description></rdf:li><rdf:li><rdf:Description xmpDM:startTime="295933" xmpDM:duration="2600" tscDM:valign="bottom" tscDM:halign="center" ><xmpDM:name><rdf:Alt><rdf:li xml:lang="en">{\rtf1 completely independent clauses you can}</rdf:li></rdf:Alt></xmpDM:name></rdf:Description></rdf:li><rdf:li><rdf:Description xmpDM:startTime="298533" xmpDM:duration="2200" tscDM:valign="bottom" tscDM:halign="center" ><xmpDM:name><rdf:Alt><rdf:li xml:lang="en">{\rtf1 connect them or join them together with}</rdf:li></rdf:Alt></xmpDM:name></rdf:Description></rdf:li><rdf:li><rdf:Description xmpDM:startTime="300733" xmpDM:duration="4233" tscDM:valign="bottom" tscDM:halign="center" ><xmpDM:name><rdf:Alt><rdf:li xml:lang="en">{\rtf1 the coordinating conjunction and so}</rdf:li></rdf:Alt></xmpDM:name></rdf:Description></rdf:li><rdf:li><rdf:Description xmpDM:startTime="304966" xmpDM:duration="1866" tscDM:valign="bottom" tscDM:halign="center" ><xmpDM:name><rdf:Alt><rdf:li xml:lang="en">{\rtf1 those are the two kinds of things you&apos;ve}</rdf:li></rdf:Alt></xmpDM:name></rdf:Description></rdf:li><rdf:li><rdf:Description xmpDM:startTime="306833" xmpDM:duration="1233" tscDM:valign="bottom" tscDM:halign="center" ><xmpDM:name><rdf:Alt><rdf:li xml:lang="en">{\rtf1 got to remember as you&apos;re thinking}</rdf:li></rdf:Alt></xmpDM:name></rdf:Description></rdf:li><rdf:li><rdf:Description xmpDM:startTime="308066" xmpDM:duration="4000" tscDM:valign="bottom" tscDM:halign="center" ><xmpDM:name><rdf:Alt><rdf:li xml:lang="en">{\rtf1 through how my punctuating coordinating}</rdf:li></rdf:Alt></xmpDM:name></rdf:Description></rdf:li><rdf:li><rdf:Description xmpDM:startTime="312066" xmpDM:duration="3333" tscDM:valign="bottom" tscDM:halign="center" ><xmpDM:name><rdf:Alt><rdf:li xml:lang="en">{\rtf1 conjunctions okay subordinate sub}</rdf:li></rdf:Alt></xmpDM:name></rdf:Description></rdf:li><rdf:li><rdf:Description xmpDM:startTime="315400" xmpDM:duration="1466" tscDM:valign="bottom" tscDM:halign="center" ><xmpDM:name><rdf:Alt><rdf:li xml:lang="en">{\rtf1 ordinate in conjunction}</rdf:li></rdf:Alt></xmpDM:name></rdf:Description></rdf:li><rdf:li><rdf:Description xmpDM:startTime="316866" xmpDM:duration="3500" tscDM:valign="bottom" tscDM:halign="center" ><xmpDM:name><rdf:Alt><rdf:li xml:lang="en">{\rtf1 these are conjunctions that connect one}</rdf:li></rdf:Alt></xmpDM:name></rdf:Description></rdf:li><rdf:li><rdf:Description xmpDM:startTime="320366" xmpDM:duration="2566" tscDM:valign="bottom" tscDM:halign="center" ><xmpDM:name><rdf:Alt><rdf:li xml:lang="en">{\rtf1 independent clause with a dependent}</rdf:li></rdf:Alt></xmpDM:name></rdf:Description></rdf:li><rdf:li><rdf:Description xmpDM:startTime="322933" xmpDM:duration="1533" tscDM:valign="bottom" tscDM:halign="center" ><xmpDM:name><rdf:Alt><rdf:li xml:lang="en">{\rtf1 clause so you&apos;ve got two different types}</rdf:li></rdf:Alt></xmpDM:name></rdf:Description></rdf:li><rdf:li><rdf:Description xmpDM:startTime="324466" xmpDM:duration="3533" tscDM:valign="bottom" tscDM:halign="center" ><xmpDM:name><rdf:Alt><rdf:li xml:lang="en">{\rtf1 of clauses here so some examples this is}</rdf:li></rdf:Alt></xmpDM:name></rdf:Description></rdf:li><rdf:li><rdf:Description xmpDM:startTime="328000" xmpDM:duration="2233" tscDM:valign="bottom" tscDM:halign="center" ><xmpDM:name><rdf:Alt><rdf:li xml:lang="en">{\rtf1 not a comprehensive list you can look in}</rdf:li></rdf:Alt></xmpDM:name></rdf:Description></rdf:li><rdf:li><rdf:Description xmpDM:startTime="330233" xmpDM:duration="2300" tscDM:valign="bottom" tscDM:halign="center" ><xmpDM:name><rdf:Alt><rdf:li xml:lang="en">{\rtf1 your textbook or online for a}</rdf:li></rdf:Alt></xmpDM:name></rdf:Description></rdf:li><rdf:li><rdf:Description xmpDM:startTime="332533" xmpDM:duration="2433" tscDM:valign="bottom" tscDM:halign="center" ><xmpDM:name><rdf:Alt><rdf:li xml:lang="en">{\rtf1 comprehensive list but some examples are}</rdf:li></rdf:Alt></xmpDM:name></rdf:Description></rdf:li><rdf:li><rdf:Description xmpDM:startTime="334966" xmpDM:duration="5566" tscDM:valign="bottom" tscDM:halign="center" ><xmpDM:name><rdf:Alt><rdf:li xml:lang="en">{\rtf1 although because since while and so our}</rdf:li></rdf:Alt></xmpDM:name></rdf:Description></rdf:li><rdf:li><rdf:Description xmpDM:startTime="340533" xmpDM:duration="1733" tscDM:valign="bottom" tscDM:halign="center" ><xmpDM:name><rdf:Alt><rdf:li xml:lang="en">{\rtf1 punctuation considerations for}</rdf:li></rdf:Alt></xmpDM:name></rdf:Description></rdf:li><rdf:li><rdf:Description xmpDM:startTime="342266" xmpDM:duration="4566" tscDM:valign="bottom" tscDM:halign="center" ><xmpDM:name><rdf:Alt><rdf:li xml:lang="en">{\rtf1 subordinating conjunctions are if you it}</rdf:li></rdf:Alt></xmpDM:name></rdf:Description></rdf:li><rdf:li><rdf:Description xmpDM:startTime="346833" xmpDM:duration="2066" tscDM:valign="bottom" tscDM:halign="center" ><xmpDM:name><rdf:Alt><rdf:li xml:lang="en">{\rtf1 you really have to think about the order}</rdf:li></rdf:Alt></xmpDM:name></rdf:Description></rdf:li><rdf:li><rdf:Description xmpDM:startTime="348900" xmpDM:duration="2800" tscDM:valign="bottom" tscDM:halign="center" ><xmpDM:name><rdf:Alt><rdf:li xml:lang="en">{\rtf1 so what is the order of the two clauses}</rdf:li></rdf:Alt></xmpDM:name></rdf:Description></rdf:li><rdf:li><rdf:Description xmpDM:startTime="351700" xmpDM:duration="1800" tscDM:valign="bottom" tscDM:halign="center" ><xmpDM:name><rdf:Alt><rdf:li xml:lang="en">{\rtf1 once you&apos;ve identified the two clauses}</rdf:li></rdf:Alt></xmpDM:name></rdf:Description></rdf:li><rdf:li><rdf:Description xmpDM:startTime="353500" xmpDM:duration="4200" tscDM:valign="bottom" tscDM:halign="center" ><xmpDM:name><rdf:Alt><rdf:li xml:lang="en">{\rtf1 if the main clause comes first there&apos;s}</rdf:li></rdf:Alt></xmpDM:name></rdf:Description></rdf:li><rdf:li><rdf:Description xmpDM:startTime="357700" xmpDM:duration="2833" tscDM:valign="bottom" tscDM:halign="center" ><xmpDM:name><rdf:Alt><rdf:li xml:lang="en">{\rtf1 no comma if the subordinate clause comes}</rdf:li></rdf:Alt></xmpDM:name></rdf:Description></rdf:li><rdf:li><rdf:Description xmpDM:startTime="360533" xmpDM:duration="3633" tscDM:valign="bottom" tscDM:halign="center" ><xmpDM:name><rdf:Alt><rdf:li xml:lang="en">{\rtf1 first there&apos;s a comma so our first}</rdf:li></rdf:Alt></xmpDM:name></rdf:Description></rdf:li><rdf:li><rdf:Description xmpDM:startTime="364166" xmpDM:duration="2533" tscDM:valign="bottom" tscDM:halign="center" ><xmpDM:name><rdf:Alt><rdf:li xml:lang="en">{\rtf1 example is I went to class that&apos;s our}</rdf:li></rdf:Alt></xmpDM:name></rdf:Description></rdf:li><rdf:li><rdf:Description xmpDM:startTime="366700" xmpDM:duration="1600" tscDM:valign="bottom" tscDM:halign="center" ><xmpDM:name><rdf:Alt><rdf:li xml:lang="en">{\rtf1 main Clause that can be a sentence by}</rdf:li></rdf:Alt></xmpDM:name></rdf:Description></rdf:li><rdf:li><rdf:Description xmpDM:startTime="368300" xmpDM:duration="3000" tscDM:valign="bottom" tscDM:halign="center" ><xmpDM:name><rdf:Alt><rdf:li xml:lang="en">{\rtf1 itself it&apos;s an independent clause and}</rdf:li></rdf:Alt></xmpDM:name></rdf:Description></rdf:li><rdf:li><rdf:Description xmpDM:startTime="371300" xmpDM:duration="1400" tscDM:valign="bottom" tscDM:halign="center" ><xmpDM:name><rdf:Alt><rdf:li xml:lang="en">{\rtf1 then we have this subordinating}</rdf:li></rdf:Alt></xmpDM:name></rdf:Description></rdf:li><rdf:li><rdf:Description xmpDM:startTime="372700" xmpDM:duration="3433" tscDM:valign="bottom" tscDM:halign="center" ><xmpDM:name><rdf:Alt><rdf:li xml:lang="en">{\rtf1 conjunction even though I was tired so}</rdf:li></rdf:Alt></xmpDM:name></rdf:Description></rdf:li><rdf:li><rdf:Description xmpDM:startTime="376133" xmpDM:duration="2566" tscDM:valign="bottom" tscDM:halign="center" ><xmpDM:name><rdf:Alt><rdf:li xml:lang="en">{\rtf1 even though I was tired as an example of}</rdf:li></rdf:Alt></xmpDM:name></rdf:Description></rdf:li><rdf:li><rdf:Description xmpDM:startTime="378700" xmpDM:duration="1800" tscDM:valign="bottom" tscDM:halign="center" ><xmpDM:name><rdf:Alt><rdf:li xml:lang="en">{\rtf1 a dependent clause that cannot stand}</rdf:li></rdf:Alt></xmpDM:name></rdf:Description></rdf:li><rdf:li><rdf:Description xmpDM:startTime="380500" xmpDM:duration="2966" tscDM:valign="bottom" tscDM:halign="center" ><xmpDM:name><rdf:Alt><rdf:li xml:lang="en">{\rtf1 alone as a sentence but because it comes}</rdf:li></rdf:Alt></xmpDM:name></rdf:Description></rdf:li><rdf:li><rdf:Description xmpDM:startTime="383466" xmpDM:duration="3300" tscDM:valign="bottom" tscDM:halign="center" ><xmpDM:name><rdf:Alt><rdf:li xml:lang="en">{\rtf1 second it comes after the main Clause we}</rdf:li></rdf:Alt></xmpDM:name></rdf:Description></rdf:li><rdf:li><rdf:Description xmpDM:startTime="386766" xmpDM:duration="1933" tscDM:valign="bottom" tscDM:halign="center" ><xmpDM:name><rdf:Alt><rdf:li xml:lang="en">{\rtf1 can connect those two things with a}</rdf:li></rdf:Alt></xmpDM:name></rdf:Description></rdf:li><rdf:li><rdf:Description xmpDM:startTime="388700" xmpDM:duration="2600" tscDM:valign="bottom" tscDM:halign="center" ><xmpDM:name><rdf:Alt><rdf:li xml:lang="en">{\rtf1 subordinating conjunction without using}</rdf:li></rdf:Alt></xmpDM:name></rdf:Description></rdf:li><rdf:li><rdf:Description xmpDM:startTime="391300" xmpDM:duration="2800" tscDM:valign="bottom" tscDM:halign="center" ><xmpDM:name><rdf:Alt><rdf:li xml:lang="en">{\rtf1 a comma our second example is just the}</rdf:li></rdf:Alt></xmpDM:name></rdf:Description></rdf:li><rdf:li><rdf:Description xmpDM:startTime="394100" xmpDM:duration="2433" tscDM:valign="bottom" tscDM:halign="center" ><xmpDM:name><rdf:Alt><rdf:li xml:lang="en">{\rtf1 opposite so we&apos;ve got a so we start with}</rdf:li></rdf:Alt></xmpDM:name></rdf:Description></rdf:li><rdf:li><rdf:Description xmpDM:startTime="396533" xmpDM:duration="1733" tscDM:valign="bottom" tscDM:halign="center" ><xmpDM:name><rdf:Alt><rdf:li xml:lang="en">{\rtf1 a subordinate clause even though I was}</rdf:li></rdf:Alt></xmpDM:name></rdf:Description></rdf:li><rdf:li><rdf:Description xmpDM:startTime="398266" xmpDM:duration="1466" tscDM:valign="bottom" tscDM:halign="center" ><xmpDM:name><rdf:Alt><rdf:li xml:lang="en">{\rtf1 tired}</rdf:li></rdf:Alt></xmpDM:name></rdf:Description></rdf:li><rdf:li><rdf:Description xmpDM:startTime="399733" xmpDM:duration="2066" tscDM:valign="bottom" tscDM:halign="center" ><xmpDM:name><rdf:Alt><rdf:li xml:lang="en">{\rtf1 and then we end with the main clause I}</rdf:li></rdf:Alt></xmpDM:name></rdf:Description></rdf:li><rdf:li><rdf:Description xmpDM:startTime="401800" xmpDM:duration="3366" tscDM:valign="bottom" tscDM:halign="center" ><xmpDM:name><rdf:Alt><rdf:li xml:lang="en">{\rtf1 went to class and so you must punctuate}</rdf:li></rdf:Alt></xmpDM:name></rdf:Description></rdf:li><rdf:li><rdf:Description xmpDM:startTime="405166" xmpDM:duration="2166" tscDM:valign="bottom" tscDM:halign="center" ><xmpDM:name><rdf:Alt><rdf:li xml:lang="en">{\rtf1 that with a comma so when you start with}</rdf:li></rdf:Alt></xmpDM:name></rdf:Description></rdf:li><rdf:li><rdf:Description xmpDM:startTime="407333" xmpDM:duration="2900" tscDM:valign="bottom" tscDM:halign="center" ><xmpDM:name><rdf:Alt><rdf:li xml:lang="en">{\rtf1 the subordinate clause and end with the}</rdf:li></rdf:Alt></xmpDM:name></rdf:Description></rdf:li><rdf:li><rdf:Description xmpDM:startTime="410233" xmpDM:duration="1366" tscDM:valign="bottom" tscDM:halign="center" ><xmpDM:name><rdf:Alt><rdf:li xml:lang="en">{\rtf1 main clause you punctuate it with a}</rdf:li></rdf:Alt></xmpDM:name></rdf:Description></rdf:li><rdf:li><rdf:Description xmpDM:startTime="411600" xmpDM:duration="3500" tscDM:valign="bottom" tscDM:halign="center" ><xmpDM:name><rdf:Alt><rdf:li xml:lang="en">{\rtf1 comma there&apos;s no real easy way for me to}</rdf:li></rdf:Alt></xmpDM:name></rdf:Description></rdf:li><rdf:li><rdf:Description xmpDM:startTime="415100" xmpDM:duration="1666" tscDM:valign="bottom" tscDM:halign="center" ><xmpDM:name><rdf:Alt><rdf:li xml:lang="en">{\rtf1 remember this I just kind of have to}</rdf:li></rdf:Alt></xmpDM:name></rdf:Description></rdf:li><rdf:li><rdf:Description xmpDM:startTime="416766" xmpDM:duration="2966" tscDM:valign="bottom" tscDM:halign="center" ><xmpDM:name><rdf:Alt><rdf:li xml:lang="en">{\rtf1 memorize that one thing that I find}</rdf:li></rdf:Alt></xmpDM:name></rdf:Description></rdf:li><rdf:li><rdf:Description xmpDM:startTime="419733" xmpDM:duration="2933" tscDM:valign="bottom" tscDM:halign="center" ><xmpDM:name><rdf:Alt><rdf:li xml:lang="en">{\rtf1 helpful when subordinating clauses come}</rdf:li></rdf:Alt></xmpDM:name></rdf:Description></rdf:li><rdf:li><rdf:Description xmpDM:startTime="422666" xmpDM:duration="1700" tscDM:valign="bottom" tscDM:halign="center" ><xmpDM:name><rdf:Alt><rdf:li xml:lang="en">{\rtf1 first they&apos;re a function much like}</rdf:li></rdf:Alt></xmpDM:name></rdf:Description></rdf:li><rdf:li><rdf:Description xmpDM:startTime="424366" xmpDM:duration="4100" tscDM:valign="bottom" tscDM:halign="center" ><xmpDM:name><rdf:Alt><rdf:li xml:lang="en">{\rtf1 introductory clauses and and you often}</rdf:li></rdf:Alt></xmpDM:name></rdf:Description></rdf:li><rdf:li><rdf:Description xmpDM:startTime="428466" xmpDM:duration="2500" tscDM:valign="bottom" tscDM:halign="center" ><xmpDM:name><rdf:Alt><rdf:li xml:lang="en">{\rtf1 put a comma after an introductory clause}</rdf:li></rdf:Alt></xmpDM:name></rdf:Description></rdf:li><rdf:li><rdf:Description xmpDM:startTime="430966" xmpDM:duration="1933" tscDM:valign="bottom" tscDM:halign="center" ><xmpDM:name><rdf:Alt><rdf:li xml:lang="en">{\rtf1 so that&apos;s maybe an easy way to also}</rdf:li></rdf:Alt></xmpDM:name></rdf:Description></rdf:li><rdf:li><rdf:Description xmpDM:startTime="432900" xmpDM:duration="4566" tscDM:valign="bottom" tscDM:halign="center" ><xmpDM:name><rdf:Alt><rdf:li xml:lang="en">{\rtf1 remember the punctuation rule okay let&apos;s}</rdf:li></rdf:Alt></xmpDM:name></rdf:Description></rdf:li><rdf:li><rdf:Description xmpDM:startTime="437466" xmpDM:duration="2966" tscDM:valign="bottom" tscDM:halign="center" ><xmpDM:name><rdf:Alt><rdf:li xml:lang="en">{\rtf1 take a second here and do a quick}</rdf:li></rdf:Alt></xmpDM:name></rdf:Description></rdf:li><rdf:li><rdf:Description xmpDM:startTime="440433" xmpDM:duration="1666" tscDM:valign="bottom" tscDM:halign="center" ><xmpDM:name><rdf:Alt><rdf:li xml:lang="en">{\rtf1 practice exercise go ahead and click}</rdf:li></rdf:Alt></xmpDM:name></rdf:Description></rdf:li><rdf:li><rdf:Description xmpDM:startTime="442100" xmpDM:duration="2800" tscDM:valign="bottom" tscDM:halign="center" ><xmpDM:name><rdf:Alt><rdf:li xml:lang="en">{\rtf1 anywhere on the video screen to launch}</rdf:li></rdf:Alt></xmpDM:name></rdf:Description></rdf:li><rdf:li><rdf:Description xmpDM:startTime="444900" xmpDM:duration="2833" tscDM:valign="bottom" tscDM:halign="center" ><xmpDM:name><rdf:Alt><rdf:li xml:lang="en">{\rtf1 the practice exercise lastly we&apos;ve got}</rdf:li></rdf:Alt></xmpDM:name></rdf:Description></rdf:li><rdf:li><rdf:Description xmpDM:startTime="447733" xmpDM:duration="1433" tscDM:valign="bottom" tscDM:halign="center" ><xmpDM:name><rdf:Alt><rdf:li xml:lang="en">{\rtf1 conjunctive adverbs}</rdf:li></rdf:Alt></xmpDM:name></rdf:Description></rdf:li><rdf:li><rdf:Description xmpDM:startTime="449166" xmpDM:duration="3233" tscDM:valign="bottom" tscDM:halign="center" ><xmpDM:name><rdf:Alt><rdf:li xml:lang="en">{\rtf1 so these join two independent clauses}</rdf:li></rdf:Alt></xmpDM:name></rdf:Description></rdf:li><rdf:li><rdf:Description xmpDM:startTime="452400" xmpDM:duration="2266" tscDM:valign="bottom" tscDM:halign="center" ><xmpDM:name><rdf:Alt><rdf:li xml:lang="en">{\rtf1 and conjunctive adverbs indicate}</rdf:li></rdf:Alt></xmpDM:name></rdf:Description></rdf:li><rdf:li><rdf:Description xmpDM:startTime="454666" xmpDM:duration="1966" tscDM:valign="bottom" tscDM:halign="center" ><xmpDM:name><rdf:Alt><rdf:li xml:lang="en">{\rtf1 relationship between those two clauses}</rdf:li></rdf:Alt></xmpDM:name></rdf:Description></rdf:li><rdf:li><rdf:Description xmpDM:startTime="456633" xmpDM:duration="3466" tscDM:valign="bottom" tscDM:halign="center" ><xmpDM:name><rdf:Alt><rdf:li xml:lang="en">{\rtf1 so again these are not comprehensive you}</rdf:li></rdf:Alt></xmpDM:name></rdf:Description></rdf:li><rdf:li><rdf:Description xmpDM:startTime="460100" xmpDM:duration="1633" tscDM:valign="bottom" tscDM:halign="center" ><xmpDM:name><rdf:Alt><rdf:li xml:lang="en">{\rtf1 can look in your textbook or online for}</rdf:li></rdf:Alt></xmpDM:name></rdf:Description></rdf:li><rdf:li><rdf:Description xmpDM:startTime="461733" xmpDM:duration="1633" tscDM:valign="bottom" tscDM:halign="center" ><xmpDM:name><rdf:Alt><rdf:li xml:lang="en">{\rtf1 a comprehensive list of conjunctive}</rdf:li></rdf:Alt></xmpDM:name></rdf:Description></rdf:li><rdf:li><rdf:Description xmpDM:startTime="463366" xmpDM:duration="4033" tscDM:valign="bottom" tscDM:halign="center" ><xmpDM:name><rdf:Alt><rdf:li xml:lang="en">{\rtf1 adverbs but however moreover and}</rdf:li></rdf:Alt></xmpDM:name></rdf:Description></rdf:li><rdf:li><rdf:Description xmpDM:startTime="467400" xmpDM:duration="1566" tscDM:valign="bottom" tscDM:halign="center" ><xmpDM:name><rdf:Alt><rdf:li xml:lang="en">{\rtf1 furthermore three examples however}</rdf:li></rdf:Alt></xmpDM:name></rdf:Description></rdf:li><rdf:li><rdf:Description xmpDM:startTime="468966" xmpDM:duration="2766" tscDM:valign="bottom" tscDM:halign="center" ><xmpDM:name><rdf:Alt><rdf:li xml:lang="en">{\rtf1 indicates contrast between two clauses}</rdf:li></rdf:Alt></xmpDM:name></rdf:Description></rdf:li><rdf:li><rdf:Description xmpDM:startTime="471733" xmpDM:duration="3766" tscDM:valign="bottom" tscDM:halign="center" ><xmpDM:name><rdf:Alt><rdf:li xml:lang="en">{\rtf1 furthermore for example it indicates two}</rdf:li></rdf:Alt></xmpDM:name></rdf:Description></rdf:li><rdf:li><rdf:Description xmpDM:startTime="475500" xmpDM:duration="2166" tscDM:valign="bottom" tscDM:halign="center" ><xmpDM:name><rdf:Alt><rdf:li xml:lang="en">{\rtf1 clauses that are agreeing or adding to}</rdf:li></rdf:Alt></xmpDM:name></rdf:Description></rdf:li><rdf:li><rdf:Description xmpDM:startTime="477666" xmpDM:duration="2033" tscDM:valign="bottom" tscDM:halign="center" ><xmpDM:name><rdf:Alt><rdf:li xml:lang="en">{\rtf1 one another so there&apos;s some relationship}</rdf:li></rdf:Alt></xmpDM:name></rdf:Description></rdf:li><rdf:li><rdf:Description xmpDM:startTime="479700" xmpDM:duration="3866" tscDM:valign="bottom" tscDM:halign="center" ><xmpDM:name><rdf:Alt><rdf:li xml:lang="en">{\rtf1 that&apos;s happening with these words to}</rdf:li></rdf:Alt></xmpDM:name></rdf:Description></rdf:li><rdf:li><rdf:Description xmpDM:startTime="483566" xmpDM:duration="2133" tscDM:valign="bottom" tscDM:halign="center" ><xmpDM:name><rdf:Alt><rdf:li xml:lang="en">{\rtf1 really just one punctuation}</rdf:li></rdf:Alt></xmpDM:name></rdf:Description></rdf:li><rdf:li><rdf:Description xmpDM:startTime="485700" xmpDM:duration="2900" tscDM:valign="bottom" tscDM:halign="center" ><xmpDM:name><rdf:Alt><rdf:li xml:lang="en">{\rtf1 consideration you always punctuate}</rdf:li></rdf:Alt></xmpDM:name></rdf:Description></rdf:li><rdf:li><rdf:Description xmpDM:startTime="488600" xmpDM:duration="2400" tscDM:valign="bottom" tscDM:halign="center" ><xmpDM:name><rdf:Alt><rdf:li xml:lang="en">{\rtf1 sentences that are connected with}</rdf:li></rdf:Alt></xmpDM:name></rdf:Description></rdf:li><rdf:li><rdf:Description xmpDM:startTime="491000" xmpDM:duration="2666" tscDM:valign="bottom" tscDM:halign="center" ><xmpDM:name><rdf:Alt><rdf:li xml:lang="en">{\rtf1 conjunctive or I&apos;m sorry clauses that}</rdf:li></rdf:Alt></xmpDM:name></rdf:Description></rdf:li><rdf:li><rdf:Description xmpDM:startTime="493666" xmpDM:duration="2100" tscDM:valign="bottom" tscDM:halign="center" ><xmpDM:name><rdf:Alt><rdf:li xml:lang="en">{\rtf1 are connected with conjunctive adverbs}</rdf:li></rdf:Alt></xmpDM:name></rdf:Description></rdf:li><rdf:li><rdf:Description xmpDM:startTime="495766" xmpDM:duration="2833" tscDM:valign="bottom" tscDM:halign="center" ><xmpDM:name><rdf:Alt><rdf:li xml:lang="en">{\rtf1 like two separate sentences okay so}</rdf:li></rdf:Alt></xmpDM:name></rdf:Description></rdf:li><rdf:li><rdf:Description xmpDM:startTime="498600" xmpDM:duration="1933" tscDM:valign="bottom" tscDM:halign="center" ><xmpDM:name><rdf:Alt><rdf:li xml:lang="en">{\rtf1 that&apos;s just an easy way to remember that}</rdf:li></rdf:Alt></xmpDM:name></rdf:Description></rdf:li><rdf:li><rdf:Description xmpDM:startTime="500533" xmpDM:duration="2733" tscDM:valign="bottom" tscDM:halign="center" ><xmpDM:name><rdf:Alt><rdf:li xml:lang="en">{\rtf1 so two examples of this I went to class}</rdf:li></rdf:Alt></xmpDM:name></rdf:Description></rdf:li><rdf:li><rdf:Description xmpDM:startTime="503266" xmpDM:duration="2433" tscDM:valign="bottom" tscDM:halign="center" ><xmpDM:name><rdf:Alt><rdf:li xml:lang="en">{\rtf1 period that&apos;s the end of us one sentence}</rdf:li></rdf:Alt></xmpDM:name></rdf:Description></rdf:li><rdf:li><rdf:Description xmpDM:startTime="505700" xmpDM:duration="3666" tscDM:valign="bottom" tscDM:halign="center" ><xmpDM:name><rdf:Alt><rdf:li xml:lang="en">{\rtf1 however comma I showed up late that&apos;s a}</rdf:li></rdf:Alt></xmpDM:name></rdf:Description></rdf:li><rdf:li><rdf:Description xmpDM:startTime="509366" xmpDM:duration="3700" tscDM:valign="bottom" tscDM:halign="center" ><xmpDM:name><rdf:Alt><rdf:li xml:lang="en">{\rtf1 second completely separate sentence or}</rdf:li></rdf:Alt></xmpDM:name></rdf:Description></rdf:li><rdf:li><rdf:Description xmpDM:startTime="513066" xmpDM:duration="2033" tscDM:valign="bottom" tscDM:halign="center" ><xmpDM:name><rdf:Alt><rdf:li xml:lang="en">{\rtf1 we can punctuate it with a semicolon I}</rdf:li></rdf:Alt></xmpDM:name></rdf:Description></rdf:li><rdf:li><rdf:Description xmpDM:startTime="515100" xmpDM:duration="2666" tscDM:valign="bottom" tscDM:halign="center" ><xmpDM:name><rdf:Alt><rdf:li xml:lang="en">{\rtf1 went to class semicolon however comma I}</rdf:li></rdf:Alt></xmpDM:name></rdf:Description></rdf:li><rdf:li><rdf:Description xmpDM:startTime="517766" xmpDM:duration="2500" tscDM:valign="bottom" tscDM:halign="center" ><xmpDM:name><rdf:Alt><rdf:li xml:lang="en">{\rtf1 showed up late we&apos;ll talk more about the}</rdf:li></rdf:Alt></xmpDM:name></rdf:Description></rdf:li><rdf:li><rdf:Description xmpDM:startTime="520266" xmpDM:duration="3233" tscDM:valign="bottom" tscDM:halign="center" ><xmpDM:name><rdf:Alt><rdf:li xml:lang="en">{\rtf1 semicolon in video three so if you&apos;re}</rdf:li></rdf:Alt></xmpDM:name></rdf:Description></rdf:li><rdf:li><rdf:Description xmpDM:startTime="523500" xmpDM:duration="3233" tscDM:valign="bottom" tscDM:halign="center" ><xmpDM:name><rdf:Alt><rdf:li xml:lang="en">{\rtf1 not clear on how the semicolon relates}</rdf:li></rdf:Alt></xmpDM:name></rdf:Description></rdf:li><rdf:li><rdf:Description xmpDM:startTime="526733" xmpDM:duration="1866" tscDM:valign="bottom" tscDM:halign="center" ><xmpDM:name><rdf:Alt><rdf:li xml:lang="en">{\rtf1 to the period and what the difference}</rdf:li></rdf:Alt></xmpDM:name></rdf:Description></rdf:li><rdf:li><rdf:Description xmpDM:startTime="528600" xmpDM:duration="1300" tscDM:valign="bottom" tscDM:halign="center" ><xmpDM:name><rdf:Alt><rdf:li xml:lang="en">{\rtf1 between the two are don&apos;t worry}</rdf:li></rdf:Alt></xmpDM:name></rdf:Description></rdf:li><rdf:li><rdf:Description xmpDM:startTime="529900" xmpDM:duration="2566" tscDM:valign="bottom" tscDM:halign="center" ><xmpDM:name><rdf:Alt><rdf:li xml:lang="en">{\rtf1 we&apos;ll talk about that more and then}</rdf:li></rdf:Alt></xmpDM:name></rdf:Description></rdf:li><rdf:li><rdf:Description xmpDM:startTime="532466" xmpDM:duration="1233" tscDM:valign="bottom" tscDM:halign="center" ><xmpDM:name><rdf:Alt><rdf:li xml:lang="en">{\rtf1 finally here&apos;s a here&apos;s a}</rdf:li></rdf:Alt></xmpDM:name></rdf:Description></rdf:li><rdf:li><rdf:Description xmpDM:startTime="533700" xmpDM:duration="2533" tscDM:valign="bottom" tscDM:halign="center" ><xmpDM:name><rdf:Alt><rdf:li xml:lang="en">{\rtf1 bad example I went to class , however I}</rdf:li></rdf:Alt></xmpDM:name></rdf:Description></rdf:li><rdf:li><rdf:Description xmpDM:startTime="536233" xmpDM:duration="2133" tscDM:valign="bottom" tscDM:halign="center" ><xmpDM:name><rdf:Alt><rdf:li xml:lang="en">{\rtf1 showed up late so punctuating that with}</rdf:li></rdf:Alt></xmpDM:name></rdf:Description></rdf:li><rdf:li><rdf:Description xmpDM:startTime="538366" xmpDM:duration="3833" tscDM:valign="bottom" tscDM:halign="center" ><xmpDM:name><rdf:Alt><rdf:li xml:lang="en">{\rtf1 a comma is incorrect it has to be}</rdf:li></rdf:Alt></xmpDM:name></rdf:Description></rdf:li><rdf:li><rdf:Description xmpDM:startTime="542200" xmpDM:duration="2966" tscDM:valign="bottom" tscDM:halign="center" ><xmpDM:name><rdf:Alt><rdf:li xml:lang="en">{\rtf1 punctuated like a period okay so now}</rdf:li></rdf:Alt></xmpDM:name></rdf:Description></rdf:li><rdf:li><rdf:Description xmpDM:startTime="545166" xmpDM:duration="4600" tscDM:valign="bottom" tscDM:halign="center" ><xmpDM:name><rdf:Alt><rdf:li xml:lang="en">{\rtf1 that we&apos;ve looked at clauses and}</rdf:li></rdf:Alt></xmpDM:name></rdf:Description></rdf:li><rdf:li><rdf:Description xmpDM:startTime="549766" xmpDM:duration="2233" tscDM:valign="bottom" tscDM:halign="center" ><xmpDM:name><rdf:Alt><rdf:li xml:lang="en">{\rtf1 conjunctions we&apos;ll do a practice}</rdf:li></rdf:Alt></xmpDM:name></rdf:Description></rdf:li><rdf:li><rdf:Description xmpDM:startTime="552000" xmpDM:duration="2366" tscDM:valign="bottom" tscDM:halign="center" ><xmpDM:name><rdf:Alt><rdf:li xml:lang="en">{\rtf1 exercise and once you&apos;re done with that}</rdf:li></rdf:Alt></xmpDM:name></rdf:Description></rdf:li><rdf:li><rdf:Description xmpDM:startTime="554366" xmpDM:duration="9600" tscDM:valign="bottom" tscDM:halign="center" ><xmpDM:name><rdf:Alt><rdf:li xml:lang="en">{\rtf1 you&apos;ll be done with video on}</rdf:li></rdf:Alt></xmpDM:name></rdf:Description></rdf:li><rdf:li><rdf:Description xmpDM:startTime="563966" xmpDM:duration="2033" tscDM:valign="bottom" tscDM:halign="center" ><xmpDM:name><rdf:Alt><rdf:li xml:lang="en">{\rtf1 you}</rdf:li></rdf:Alt></xmpDM:name></rdf:Description></rdf:li></rdf:Seq></xmpDM:markers><tsc:fgColor xmpG:red="255" xmpG:green="255" xmpG:blue="255" xmpG:mode="RGB" ></tsc:fgColor><tsc:bgColor xmpG:red="0" xmpG:green="0" xmpG:blue="0" xmpG:mode="RGB" ></tsc:bgColor></rdf:Description></rdf:li><rdf:li><rdf:Description xmpDM:trackType="TableOfContents" xmpDM:trackName="Table of Contents" xmpDM:frameRate="f1000" tscDM:image="" tscDM:tocCellLayout="both" ><xmpDM:markers><rdf:Seq><rdf:li><rdf:Description xmpDM:name="Defining Clauses" xmpDM:startTime="22000" tscDM:image="TocThumbnails.png" tscDM:imageindex="0" tscDM:imageoffset="0" tscDM:imagerect="0,0,200,90" ></rdf:Description></rdf:li><rdf:li><rdf:Description xmpDM:name="Practice Exercise #1" xmpDM:startTime="135133" tscDM:image="TocThumbnails.png" tscDM:imageindex="1" tscDM:imageoffset="1" tscDM:imagerect="200,0,200,90" ></rdf:Description></rdf:li><rdf:li><rdf:Description xmpDM:name="3 Types of Conjunctions" xmpDM:startTime="151400" tscDM:image="TocThumbnails.png" tscDM:imageindex="2" tscDM:imageoffset="2" tscDM:imagerect="400,0,200,90" ></rdf:Description></rdf:li><rdf:li><rdf:Description xmpDM:name="Coordinating Conjunctions" xmpDM:startTime="180633" tscDM:image="TocThumbnails.png" tscDM:imageindex="3" tscDM:imageoffset="3" tscDM:imagerect="600,0,200,90" ></rdf:Description></rdf:li><rdf:li><rdf:Description xmpDM:name="Subordinating Conjunctions" xmpDM:startTime="314766" tscDM:image="TocThumbnails.png" tscDM:imageindex="4" tscDM:imageoffset="4" tscDM:imagerect="800,0,200,90" ></rdf:Description></rdf:li><rdf:li><rdf:Description xmpDM:name="Practice Exercise #2" xmpDM:startTime="436333" tscDM:image="TocThumbnails.png" tscDM:imageindex="5" tscDM:imageoffset="5" tscDM:imagerect="1000,0,200,90" ></rdf:Description></rdf:li><rdf:li><rdf:Description xmpDM:name="Conjunctive Adverbs" xmpDM:startTime="447366" tscDM:image="TocThumbnails.png" tscDM:imageindex="6" tscDM:imageoffset="6" tscDM:imagerect="1200,0,200,90" ></rdf:Description></rdf:li><rdf:li><rdf:Description xmpDM:name="Practice Exercise #3" xmpDM:startTime="556900" tscDM:image="TocThumbnails.png" tscDM:imageindex="7" tscDM:imageoffset="7" tscDM:imagerect="1400,0,200,90" ></rdf:Description></rdf:li></rdf:Seq></xmpDM:markers></rdf:Description></rdf:li><rdf:li><rdf:Description xmpDM:trackType="Hotspot" xmpDM:frameRate="f1000" xmpDM:trackName="Hotspots" ><xmpDM:markers><rdf:Seq><rdf:li><rdf:Description xmp:label="1" xmpDM:startTime="134966" xmpDM:duration="10766" tscDM:boundingPoly="296,10;1144,10;1144,515;296,515;" tscDM:rotate="0" tscHS:pause="1" xmpDM:location="https://unt.instructure.com/courses/723/quizzes/3420" tscHS:newWindow="1" ></rdf:Description></rdf:li><rdf:li><rdf:Description xmp:label="2" xmpDM:startTime="436033" xmpDM:duration="10766" tscDM:boundingPoly="311,16;1144,16;1144,511;311,511;" tscDM:rotate="0" tscHS:pause="1" xmpDM:location="https://unt.instructure.com/courses/723/quizzes/3421" tscHS:newWindow="1" ></rdf:Description></rdf:li><rdf:li><rdf:Description xmp:label="3" xmpDM:startTime="556466" xmpDM:duration="9533" tscDM:boundingPoly="332,20;1149,20;1149,505;332,505;" tscDM:rotate="0" tscHS:pause="1" xmpDM:location="https://unt.instructure.com/courses/723/quizzes/3422" tscHS:newWindow="1" ></rdf:Description></rdf:li></rdf:Seq></xmpDM:markers></rdf:Description></rdf:li></rdf:Bag></xmpDM:Tracks><tscDM:controller><rdf:Description xmpDM:name="tscplayer" ><tscDM:parameters><rdf:Bag><rdf:li xmpDM:name="autohide" xmpDM:value="true" ></rdf:li><rdf:li xmpDM:name="autoplay" xmpDM:value="false" ></rdf:li><rdf:li xmpDM:name="backgroundcolor" xmpDM:value="000000" ></rdf:li><rdf:li xmpDM:name="captionsenabled" xmpDM:value="false" ></rdf:li><rdf:li xmpDM:name="endaction" xmpDM:value="stop" ></rdf:li><rdf:li xmpDM:name="endactionparam" xmpDM:value="true" ></rdf:li><rdf:li xmpDM:name="locale" xmpDM:value="en-US" ></rdf:li><rdf:li xmpDM:name="searchable" xmpDM:value="true" ></rdf:li><rdf:li xmpDM:name="sidebarenabled" xmpDM:value="false" ></rdf:li><rdf:li xmpDM:name="sidebarlocation" xmpDM:value="left" ></rdf:li><rdf:li xmpDM:name="unicodeenabled" xmpDM:value="false" ></rdf:li></rdf:Bag></tscDM:parameters><tscDM:controllerText><rdf:Bag><rdf:li><rdf:Description xmp:label="localSecurityError" ><tscDM:localizedText><rdf:Alt><rdf:li xml:lang="en-US">Certain features in your video are currently disabled due to Local Network Security. These features work correctly when the video is played from a Website or Server.</rdf:li></rdf:Alt></tscDM:localizedText></rdf:Description></rdf:li><rdf:li><rdf:Description xmp:label="replayButtonText" ><tscDM:localizedText><rdf:Alt><rdf:li xml:lang="en-US">Replay</rdf:li></rdf:Alt></tscDM:localizedText></rdf:Description></rdf:li><rdf:li><rdf:Description xmp:label="resultText" ><tscDM:localizedText><rdf:Alt><rdf:li xml:lang="en-US">Results Found</rdf:li></rdf:Alt></tscDM:localizedText></rdf:Description></rdf:li><rdf:li><rdf:Description xmp:label="searchFullscreenText" ><tscDM:localizedText><rdf:Alt><rdf:li xml:lang="en-US">Search disabled in full screen mode</rdf:li></rdf:Alt></tscDM:localizedText></rdf:Description></rdf:li><rdf:li><rdf:Description xmp:label="searchText" ><tscDM:localizedText><rdf:Alt><rdf:li xml:lang="en-US">Search</rdf:li></rdf:Alt></tscDM:localizedText></rdf:Description></rdf:li></rdf:Bag></tscDM:controllerText></rdf:Description></tscDM:controller><tscDM:contentList><rdf:Description><tscDM:files><rdf:Seq><rdf:li xmpDM:name="1" xmpDM:value="new-punctuation-video1-newest-fixed.mp4"></rdf:li><rdf:li xmpDM:name="2" xmpDM:value="TocThumbnails.png"></rdf:li></rdf:Seq></tscDM:files></rdf:Description></tscDM:contentList></rdf:Description></rdf:RDF></x:xmpmeta>